gym_lqr/__init__.py
gym_lqr/compleib.py
gym_lqr/utils.py
gym_lqr/envs/__init__.py
gym_lqr/envs/lqr.py
gym_lqr-0.0.2.dist-info/licenses/LICENSE
gym_lqr-0.0.2.dist-info/METADATA
gym_lqr-0.0.2.dist-info/WHEEL
gym_lqr-0.0.2.dist-info/top_level.txt
gym_lqr-0.0.2.dist-info/RECORD
