Metadata-Version: 2.4
Name: gym-lqr
Version: 0.0.2
Summary: Gym(nasium) Interface for LQR-Family Problems
Author: Nick Korbit
Platform: any
Classifier: Programming Language :: Python :: 3.10
Classifier: Programming Language :: Python :: 3.11
Classifier: Programming Language :: Python :: 3.12
Classifier: Operating System :: OS Independent
Classifier: Topic :: Scientific/Engineering :: Artificial Intelligence
License-File: LICENSE
Requires-Dist: numpy
Requires-Dist: scipy
Requires-Dist: gymnasium>=0.26.1
Dynamic: author
Dynamic: classifier
Dynamic: description
Dynamic: description-content-type
Dynamic: license-file
Dynamic: platform
Dynamic: requires-dist
Dynamic: summary
